{
  "A": {
    "0": "1★ 尼多朗",
    "1": "3★ 暴飛龍",
    "2": "5★ 達克萊伊",
    "3": "3★ 大比鳥",
    "4": "1★ 尼多蘭",
    "5": "3★ 火伊布",
    "6": "2★ 海魔獅",
    "7": "3★ 尼多王",
    "8": "2★ 堅果啞鈴",
    "9": "2★ 甲殼龍",
    "10": "2★ 卡咪龜",
    "11": "4★ 水箭龜",
    "12": "1★ 海豹球",
    "13": "3★ 爆焰龜獸",
    "14": "2★ 伊布",
    "15": "2★ 尼多力諾",
    "16": "2★ 尼多娜",
    "17": "1★ 波波",
    "18": "1★ 寶貝龍",
    "19": "2★ 大岩蛇",
    "20": "3★ 迷你Q",
    "21": "5★ 噴火龍",
    "22": "4★ 雙斧戰龍",
    "23": "1★ 波波",
    "24": "1★ 傑尼龜",
    "25": "4★ 炎帝",
    "26": "1★ 種子鐵球",
    "27": "2★ 皮卡丘",
    "28": "1★ 牙牙",
    "29": "1★ 傑尼龜",
    "30": "3★ 水箭龜",
    "31": "2★ 火恐龍",
    "32": "4★ 皮卡丘",
    "33": "4★ 妙蛙花",
    "34": "2★ 尼多利諾",
    "35": "2★ 伊布",
    "36": "3★ 帝牙海獅",
    "37": "2★ 釜牙龍",
    "38": "2★ 比比鳥",
    "39": "4★ 水伊布",
    "40": "1★ 小火龍",
    "41": "2★ 火恐龍",
    "42": "2★ 妙蛙草",
    "43": "4★ 暴鯉龍",
    "44": "3★ 尼多后",
    "45": "2★ 甲殼龍",
    "46": "2★ 妙蛙草",
    "47": "2★ 比比鳥",
    "48": "2★ 堅果啞鈴",
    "49": "2★ 大岩蛇"
  },
  "B": {
    "0": "2★ 卡咪龜",
    "1": "4★ 雷公",
    "2": "3★ 雙斧戰龍",
    "3": "2★ 甲殼龍",
    "4": "3★ 皮卡丘",
    "5": "5★ 拉帝歐斯",
    "6": "1★ 波波",
    "7": "2★ 比比鳥",
    "8": "2★ 尼多力諾",
    "9": "1★ 小火龍",
    "10": "3★ 皮卡丘",
    "11": "3★ 噴火龍",
    "12": "3★ 大比鳥",
    "13": "2★ 火恐龍",
    "14": "3★ 雷伊布",
    "15": "2★ 卡咪龜",
    "16": "2★ 大岩蛇",
    "17": "2★ 斧牙龍",
    "18": "3★ 大鋼蛇",
    "19": "3★ 迷你Q",
    "20": "2★ 火恐龍",
    "21": "1★ 妙蛙種子",
    "22": "2★ 尼多娜",
    "23": "3★ 水伊布",
    "24": "1★ 尼多朗",
    "25": "2★ 斧牙龍",
    "26": "4★ 暴飛龍",
    "27": "1★ 寶貝龍",
    "28": "1★ 海豹球",
    "29": "1★ 牙牙",
    "30": "2★ 大岩蛇",
    "31": "4★ 尼多王",
    "32": "3★ 伊布",
    "33": "1★ 海豹球",
    "34": "2★ 尼多利諾",
    "35": "3★ 爆焰龜獸",
    "36": "4★ 水君",
    "37": "5★ 超夢",
    "38": "2★ 堅果啞鈴",
    "39": "2★ 伊布",
    "40": "2★ 海魔獅",
    "41": "4★ 雷伊布",
    "42": "1★ 尼多朗",
    "43": "1★ 寶貝龍",
    "44": "1★ 妙蛙種子",
    "45": "2★ 皮卡丘",
    "46": "2★ 海魔獅",
    "47": "2★ 妙蛙草",
    "48": "4★ 帝牙海獅",
    "49": "1★ 種子鐵球"
  },
  "C": {
    "0": "2★ 大岩蛇",
    "1": "2★ 尼多娜",
    "2": "4★ 雷公",
    "3": "1★ 尼多朗",
    "4": "2★ 甲殼龍",
    "5": "3★ 迷你Q",
    "6": "2★ 伊布",
    "7": "3★ 大比鳥",
    "8": "1★ 尼多蘭",
    "9": "1★ 種子鐵球",
    "10": "1★ 妙蛙種子",
    "11": "3★ 暴飛龍",
    "12": "5★ 四顎針龍",
    "13": "3★ 帝牙海獅",
    "14": "2★ 妙蛙草",
    "15": "4★ 妙蛙花",
    "16": "2★ 斧牙龍",
    "17": "2★ 卡咪龜",
    "18": "4★ 雙斧戰龍",
    "19": "2★ 海魔獅",
    "20": "2★ 尼多娜",
    "21": "4★ 帝牙海獅",
    "22": "4★ 水伊布",
    "23": "1★ 傑尼龜",
    "24": "2★ 比比鳥",
    "25": "3★ 尼多王",
    "26": "1★ 牙牙",
    "27": "4★ 炎帝",
    "28": "3★ 尼多后",
    "29": "1★ 種子鐵球",
    "30": "2★ 比比鳥",
    "31": "3★ 爆焰龜獸",
    "32": "4★ 皮卡丘",
    "33": "3★ 雷伊布",
    "34": "1★ 寶貝龍",
    "35": "1★ 海豹球",
    "36": "2★ 皮卡丘",
    "37": "2★ 堅果啞鈴",
    "38": "1★ 波波",
    "39": "2★ 海魔獅",
    "40": "1★ 寶貝龍",
    "41": "2★ 火恐龍",
    "42": "5★ 基格爾德",
    "43": "2★ 皮卡丘",
    "44": "1★ 小火龍",
    "45": "3★ 妙蛙花",
    "46": "2★ 尼多利諾",
    "47": "2★ 卡咪龜",
    "48": "2★ 釜牙龍",
    "49": "3★ 噴火龍"
  },
  "D": {
    "0": "2★ 斧牙龍",
    "1": "1★ 尼多朗",
    "2": "2★ 尼多力諾",
    "3": "2★ 堅果啞鈴",
    "4": "1★ 寶貝龍",
    "5": "4★ 大鋼蛇",
    "6": "3★ 堅果啞鈴",
    "7": "3★ 雙斧戰龍",
    "8": "2★ 海魔獅",
    "9": "2★ 皮卡丘",
    "10": "3★ 伊布",
    "11": "1★ 海豹球",
    "12": "5★ 噴火龍",
    "13": "1★ 傑尼龜",
    "14": "3★ 水伊布",
    "15": "2★ 大岩蛇",
    "16": "1★ 小火龍",
    "17": "3★ 雷伊布",
    "18": "2★ 比比鳥",
    "19": "1★ 牙牙",
    "20": "2★ 火恐龍",
    "21": "2★ 妙蛙草",
    "22": "4★ 炎帝",
    "23": "2★ 甲殼龍",
    "24": "4★ 暴飛龍",
    "25": "2★ 海魔獅",
    "26": "2★ 妙蛙草",
    "27": "2★ 伊布",
    "28": "3★ 暴鯉龍",
    "29": "4★ 尼多后",
    "30": "5★ 惡食大王",
    "31": "1★ 尼多朗",
    "32": "1★ 傑尼龜",
    "33": "1★ 牙牙",
    "34": "2★ 尼多娜",
    "35": "3★ 水箭龜",
    "36": "2★ 卡咪 龜",
    "37": "4★ 雷伊布",
    "38": "4★ 水君",
    "39": "2★ 卡咪龜",
    "40": "2★ 大岩蛇",
    "41": "2★ 甲殼龍",
    "42": "3★ 皮卡丘",
    "43": "3★ 大鋼蛇",
    "44": "1★ 種子鐵球",
    "45": "4★ 噴火龍",
    "46": "2★ 堅果啞鈴",
    "47": "1★ 妙蛙種子",
    "48": "2★ 伊布",
    "49": "2★ 尼多娜"
  },
  "E": {
    "0": "3★ 皮卡丘",
    "1": "2★ 海魔獅",
    "2": "1★ 海豹球",
    "3": "2★ 皮卡丘",
    "4": "1★ 小火龍",
    "5": "1★ 種子鐵球",
    "6": "2★ 尼多力諾",
    "7": "4★ 大比鳥",
    "8": "2★ 堅果啞鈴",
    "9": "2★ 妙蛙草",
    "10": "2★ 大岩蛇",
    "11": "2★ 妙蛙草",
    "12": "5★ 拉帝亞斯",
    "13": "4★ 大鋼蛇",
    "14": "1★ 尼多蘭",
    "15": "1★ 小火龍",
    "16": "3★ 爆焰龜獸",
    "17": "4★ 雷公",
    "18": "1★ 尼多蘭",
    "19": "3★ 大比鳥",
    "20": "2★ 甲殼龍",
    "21": "1★ 尼多朗",
    "22": "2★ 比比鳥",
    "23": "1★ 傑尼龜",
    "24": "3★ 帝牙海獅",
    "25": "2★ 火恐龍",
    "26": "2★ 伊布",
    "27": "2★ 釜牙龍",
    "28": "2★ 皮卡丘",
    "29": "2★ 堅果啞鈴",
    "30": "2★ 伊布",
    "31": "3★ 妙蛙花",
    "32": "2★ 尼多利諾",
    "33": "3★ 尼多后",
    "34": "2★ 火恐龍",
    "35": "3★ 迷你Q",
    "36": "2★ 卡咪龜",
    "37": "1★ 妙蛙種子",
    "38": "1★ 波波",
    "39": "3★ 水伊布",
    "40": "4★ 水箭龜",
    "41": "1★ 尼多朗",
    "42": "4★ 尼多王",
    "43": "3★ 火伊布",
    "44": "2★ 尼多娜",
    "45": "3★ 噴火龍",
    "46": "4★ 火伊布",
    "47": "2★ 比比鳥",
    "48": "3★ 大鋼蛇",
    "49": "5★ 甲賀忍蛙"
  },
  "F": {
    "0": "4★ 暴鯉龍",
    "1": "5★ 阿爾宙斯",
    "2": "3★ 雷伊布",
    "3": "3★ 堅果啞鈴",
    "4": "4★ 尼多后",
    "5": "2★ 尼多 娜",
    "6": "2★ 卡咪龜",
    "7": "4★ 皮卡丘",
    "8": "1★ 波波",
    "9": "3★ 尼多王",
    "10": "2★ 妙蛙草",
    "11": "3★ 雙斧戰龍",
    "12": "4★ 噴火龍",
    "13": "1★ 尼多蘭",
    "14": "1★ 小火龍",
    "15": "3★ 伊布",
    "16": "3★ 暴鯉龍",
    "17": "2★ 伊布",
    "18": "2★ 斧牙龍",
    "19": "1★ 尼多朗",
    "20": "2★ 尼多娜",
    "21": "2★ 比比鳥",
    "22": "2★ 尼多力諾",
    "23": "2★ 大岩蛇",
    "24": "2★ 甲殼龍",
    "25": "2★ 火恐龍",
    "26": "2★ 堅果啞鈴",
    "27": "1★ 寶貝龍",
    "28": "3★ 皮卡丘",
    "29": "2★ 妙蛙草",
    "30": "3★ 大鋼蛇",
    "31": "4★ 雷伊布",
    "32": "5★ 超夢",
    "33": "2★ 海魔獅",
    "34": "1★ 種子鐵球",
    "35": "4★ 雷公",
    "36": "2★ 火恐龍",
    "37": "2★ 皮卡丘",
    "38": "1★ 妙蛙種子",
    "39": "1★ 海豹球",
    "40": "1★ 牙牙",
    "41": "4★ 水君",
    "42": "3★ 妙蛙花",
    "43": "2★ 比比鳥",
    "44": "1★ 傑尼龜",
    "45": "3★ 水箭龜",
    "46": "2★ 皮卡丘",
    "47": "1★ 傑尼龜",
    "48": "2★ 釜牙龍",
    "49": "2★ 伊布"
  },
  "G": {
    "0": "4★ 火伊布",
    "1": "2★ 海魔獅",
    "2": "2★ 大岩 蛇",
    "3": "1★ 牙牙",
    "4": "1★ 海豹球",
    "5": "1★ 種子鐵球",
    "6": "2★ 堅果啞鈴",
    "7": "5★ 路奈亞拉",
    "8": "1★ 尼多朗",
    "9": "4★ 水君",
    "10": "2★ 甲殼龍",
    "11": "3★ 暴飛龍",
    "12": "3★ 雙斧戰龍",
    "13": "2★ 伊布",
    "14": "3★ 噴火龍",
    "15": "2★ 妙蛙草",
    "16": "2★ 斧牙龍",
    "17": "2★ 尼多娜",
    "18": "1★ 寶貝龍",
    "19": "3★ 火伊布",
    "20": "2★ 皮卡丘",
    "21": "1★ 妙蛙種子",
    "22": "1★ 波波",
    "23": "2★ 大岩蛇",
    "24": "1★ 尼多蘭",
    "25": "4★ 大比鳥",
    "26": "2★ 尼多利諾",
    "27": "2★ 火恐龍",
    "28": "2★ 卡咪龜",
    "29": "3★ 水伊布",
    "30": "2★ 皮卡丘",
    "31": "1★ 牙牙",
    "32": "3★ 暴鯉龍",
    "33": "4★ 噴火龍",
    "34": "5★ 甲賀忍蛙",
    "35": "3★ 堅果啞鈴",
    "36": "1★ 傑尼龜",
    "37": "4★ 火伊布",
    "38": "3★ 迷你Q",
    "39": "2★ 尼多娜",
    "40": "3★ 帝牙海獅",
    "41": "2★ 比比鳥",
    "42": "1★ 小火龍",
    "43": "4★ 尼多王",
    "44": "2★ 堅果啞鈴",
    "45": "4★ 爆焰龜獸",
    "46": "2★ 妙蛙草",
    "47": "2★ 海魔獅",
    "48": "2★ 卡咪龜",
    "49": "2★ 甲殼龍"
  },
  "H": {
    "0": "4★ 爆焰龜獸",
    "1": "3★ 堅果啞鈴",
    "2": "4★ 水箭龜",
    "3": "2★ 火恐龍",
    "4": "1★ 小火龍",
    "5": "2★ 大岩蛇",
    "6": "2★ 甲殼龍",
    "7": "2★ 伊布",
    "8": "1★ 波波",
    "9": "2★ 卡咪龜",
    "10": "1★ 尼多蘭",
    "11": "5★ 阿爾宙斯",
    "12": "2★ 斧牙龍",
    "13": "3★ 尼多后",
    "14": "2★ 伊布",
    "15": "1★ 波波",
    "16": "3★ 水箭龜",
    "17": "3★ 暴鯉龍",
    "18": "3★ 火伊布",
    "19": "1★ 牙牙",
    "20": "2★ 尼多力諾",
    "21": "2★ 甲殼龍",
    "22": "1★ 寶貝龍",
    "23": "2★ 海魔獅",
    "24": "2★ 尼多娜",
    "25": "1★ 傑尼龜",
    "26": "2★ 皮卡丘",
    "27": "2★ 妙蛙草",
    "28": "4★ 炎帝",
    "29": "1★ 尼多朗",
    "30": "3★ 迷你Q",
    "31": "2★ 比比鳥",
    "32": "1★ 種子鐵球",
    "33": "3★ 伊布",
    "34": "4★ 尼多后",
    "35": "4★ 暴鯉龍",
    "36": "2★ 火恐龍",
    "37": "3★ 尼多王",
    "38": "2★ 尼多利諾",
    "39": "2★ 釜牙龍",
    "40": "3★ 妙蛙花",
    "41": "5★ 索爾迦雷歐",
    "42": "4★ 水伊布",
    "43": "1★ 妙蛙種子",
    "44": "2★ 比比鳥",
    "45": "2★ 卡咪龜",
    "46": "2★ 堅果啞鈴",
    "47": "1★ 海豹球",
    "48": "3★ 暴飛龍",
    "49": "4★ 妙蛙花"
  }
}
